dm_core/__init__.py
dm_core/redis/__init__.py
dm_core/redis/apps.py
dm_core/redis/datetime_util.py
dm_core/redis/email_handler.py
dm_core/redis/service.py
dm_core/redis/utils.py
dm_core/redis/tests/__init__.py
dm_core_redis-1.0.1.dist-info/licenses/LICENSE
dm_core_redis-1.0.1.dist-info/METADATA
dm_core_redis-1.0.1.dist-info/WHEEL
dm_core_redis-1.0.1.dist-info/top_level.txt
dm_core_redis-1.0.1.dist-info/RECORD
